WorQ-1.1.1.dist-info/DESCRIPTION.rst
WorQ-1.1.1.dist-info/METADATA
WorQ-1.1.1.dist-info/RECORD
WorQ-1.1.1.dist-info/WHEEL
WorQ-1.1.1.dist-info/metadata.json
WorQ-1.1.1.dist-info/top_level.txt
worq/__init__.py
worq/const.py
worq/core.py
worq/task.py
worq/pool/__init__.py
worq/pool/process.py
worq/pool/thread.py
worq/queue/__init__.py
worq/queue/memory.py
worq/queue/redis.py
worq/tests/__init__.py
worq/tests/test_core.py
worq/tests/test_examples.py
worq/tests/test_task.py
worq/tests/util.py
worq/tests/pool/__init__.py
worq/tests/pool/test_process.py
