Metadata-Version: 2.0
Name: WorQ
Version: 1.1.1
Summary: Python task queue
Home-page: http://worq.readthedocs.org/
Author: Daniel Miller
Author-email: millerdev@gmail.com
License: LICENSE.txt
Platform: UNKNOWN
Classifier: Programming Language :: Python
Classifier: Programming Language :: Python :: 2.7
Classifier: Programming Language :: Python :: 3
Classifier: Development Status :: 4 - Beta
Classifier: Environment :: Other Environment
Classifier: Intended Audience :: Developers
Classifier: License :: OSI Approved :: MIT License
Classifier: Operating System :: OS Independent
Classifier: Topic :: Software Development :: Libraries :: Python Modules
Provides-Extra: redis
Provides-Extra: redis
Requires-Dist: redis (>=2.4); extra == 'redis'
